{
  "chunk_id": "36472ded-9810-49f8-8850-9a72735dfd20",
  "text": "dividends from stocks and mutual funds and to avoid confusion that the dividend option was a \nguaranteed bonus. \n \n33) What is the timeline for transfer of IDCW and redemption proceeds to \ninvestors/unitholders: \n \nThe payment of IDCW (dividend) proceeds to the investors/unitholders shall be made within seven \nworking days from the record date*. The transfer of redemption or repurchase proceeds to the",
  "metadata": {
    "source_url": "https://www.sebi.gov.in/sebi_data/faqfiles/sep-2024/1727242783639.pdf",
    "source_id": "src_004",
    "scheme_name": "general",
    "doc_type": "regulatory",
    "section": null,
    "page_number": null,
    "last_updated": "2026-04-16",
    "chunk_index": 83,
    "total_chunks": 108,
    "raw_file": "data/raw/pdf/regulatory_src_004_sebi-data-faqfiles-sep-2024-1727242783639-pdf_20260416.pdf"
  }
}